learning_loop_node/__init__.py
learning_loop_node/data_exchanger.py
learning_loop_node/globals.py
learning_loop_node/loop_communication.py
learning_loop_node/node.py
learning_loop_node/py.typed
learning_loop_node/rest.py
learning_loop_node/annotation/__init__.py
learning_loop_node/annotation/annotator_logic.py
learning_loop_node/annotation/annotator_node.py
learning_loop_node/data_classes/__init__.py
learning_loop_node/data_classes/annotation_data.py
learning_loop_node/data_classes/annotations.py
learning_loop_node/data_classes/detections.py
learning_loop_node/data_classes/general.py
learning_loop_node/data_classes/image_metadata.py
learning_loop_node/data_classes/socket_response.py
learning_loop_node/data_classes/training.py
learning_loop_node/detector/__init__.py
learning_loop_node/detector/detector_logic.py
learning_loop_node/detector/detector_node.py
learning_loop_node/detector/exceptions.py
learning_loop_node/detector/outbox.py
learning_loop_node/detector/inbox_filter/__init__.py
learning_loop_node/detector/inbox_filter/cam_observation_history.py
learning_loop_node/detector/inbox_filter/relevance_filter.py
learning_loop_node/detector/rest/__init__.py
learning_loop_node/detector/rest/about.py
learning_loop_node/detector/rest/backdoor_controls.py
learning_loop_node/detector/rest/detect.py
learning_loop_node/detector/rest/model_version_control.py
learning_loop_node/detector/rest/operation_mode.py
learning_loop_node/detector/rest/outbox_mode.py
learning_loop_node/detector/rest/upload.py
learning_loop_node/enums/__init__.py
learning_loop_node/enums/annotator.py
learning_loop_node/enums/detector.py
learning_loop_node/enums/general.py
learning_loop_node/enums/trainer.py
learning_loop_node/helpers/__init__.py
learning_loop_node/helpers/background_tasks.py
learning_loop_node/helpers/environment_reader.py
learning_loop_node/helpers/gdrive_downloader.py
learning_loop_node/helpers/log_conf.py
learning_loop_node/helpers/misc.py
learning_loop_node/helpers/run.py
learning_loop_node-0.18.4.dist-info/METADATA
learning_loop_node-0.18.4.dist-info/WHEEL
learning_loop_node-0.18.4.dist-info/top_level.txt
learning_loop_node-0.18.4.dist-info/RECORD
