Metadata-Version: 2.4
Name: learning_loop_node
Version: 0.18.4
Summary: Python Library for Nodes which connect to the Zauberzeug Learning Loop
Author-email: Zauberzeug GmbH <info@zauberzeug.com>
License: MIT
Project-URL: Repository, https://github.com/zauberzeug/learning_loop_node
Requires-Python: >=3.9
Requires-Dist: fastapi<1.0,>=0.128
Requires-Dist: uvicorn[standard]<0.23.0,>=0.22.0
Requires-Dist: fastapi-utils<0.9.0,>=0.8.0
Requires-Dist: requests<3.0.0,>=2.25.1
Requires-Dist: python-socketio<6.0.0,>=5.7.2
Requires-Dist: simplejson<4.0.0,>=3.17.2
Requires-Dist: icecream<3.0.0,>=2.1.0
Requires-Dist: aiofiles<0.8.0,>=0.7.0
Requires-Dist: async_generator<2.0.0,>=1.10
Requires-Dist: pytest-watch<5.0.0,>=4.2.0
Requires-Dist: python-multipart<0.0.19,>=0.0.18
Requires-Dist: psutil<6.0.0,>=5.8.0
Requires-Dist: numpy<3.0,>=2.0
Requires-Dist: Pillow<12.0.0,>=11.0.0
Requires-Dist: tqdm<5.0.0,>=4.66.3
Requires-Dist: pytest-mock<4.0.0,>=3.6.1
Requires-Dist: pynvml<12.0.0,>=11.4.1
Requires-Dist: aiohttp<4.0.0,>=3.13.3
Requires-Dist: httpx<0.29.0,>=0.28.1
Requires-Dist: dacite<2.0.0,>=1.8.1
Provides-Extra: dev
Requires-Dist: pytest-flakefinder<2.0.0,>=1.1.0; extra == "dev"
Requires-Dist: retry<0.10.0,>=0.9.2; extra == "dev"
Requires-Dist: debugpy<2.0.0,>=1.6.7.post1; extra == "dev"
Requires-Dist: pytest-asyncio<0.22.0,>=0.21.1; extra == "dev"
Requires-Dist: autopep8<3.0.0,>=2.0.2; extra == "dev"
